[
    {
        "id": "0",
        "imagem": "https://imagens.trocafone.com/images/phones/dt-591c9c9f-iphone7-black-1.jpg",
        "titulo": "iPhone 7 Plus Preto Matte",
        "preco": "1899,90",
        "parcela": "ou 12x de R$ 59,99 sem juros",
        "tituloDetalhe": "iPhone 7 Plus 32GB Preto Matte Desbloqueado IOS 10",
        "marca": "Apple",
        "modelo": "iPhone 7",
        "cor": "Preto",
        "chip": "Nano Chip",
        "qtd_chip": "Single Chip",
        "memoria_interna": "32GB",
        "memoria_ram": "2GB",
        "processador": "A10",
        "sistema": "Iphone IOS",
        "versao": "IOS 10",
        "tipo_tela": "Retina Display",
        "tamanho_display": "4.7'",
        "resolucao": "1334 x 750 pixels, 326 ppp",
        "camera_traseira": "12MP",
        "camera_frontal": "7MP",
        "lado": "https://imagens.trocafone.com/images/phones/dt-58ab0bac-iphone7-black-2.jpg",
        "traseira": "https://imagens.trocafone.com/images/phones/dt-58ab0bad-iphone7-black-3.jpg"
    },

    {
        "id": "1",
        "imagem": "https://imagens.trocafone.com/images/phones/dt-5ab2a7f1-iphone-x-cinzaespacial-frente.png",
        "titulo": "Iphone X Cinza Espacial",
        "preco": "2000,00",
        "parcela": "ou 12X de 49,60 sem juros",
        "tituloDetalhe": "iPhone X Cinza Espacial 64GB Tela 5.8",
        "marca": "Apple",
        "modelo": "Iphone X Space Gray 64GB-BRA",
        "cor": "Cinza",
        "chip": "Nano Chip",
        "qtd_chip": "Single Chip",
        "memoria_interna": "64GB",
        "memoria_ram": "2GB",
        "processador": "A11 Bionic com arquitetura de 64 bits",
        "sistema": "Iphone IOS",
        "versao": "11",
        "tipo_tela": "oled",
        "tamanho_display": "5.8'",
        "resolucao": "Resolução de 2436 x 1125 pixels a 458 ppp",
        "camera_traseira": "12MP",
        "camera_frontal": "7MP",
        "lado": "https://imagens.trocafone.com/images/phones/dt-5ab2a7f1-iphone-x-cinzaespacial-perfil.png",
        "traseira": "https://imagens.trocafone.com/images/phones/dt-5ab2a7f2-iphone-x-cinzaespacial-traseira.png"
    },

    {
        "id": "2",
        "imagem": "https://imagens.trocafone.com/images/phones/dt-motorola-moto-maxx-2-64gb.jpg",
        "titulo": "Motorola Moto Maxx 2 64gb",
        "preco": "2000,00",
        "parcela": "ou 12x R$ 49,90 sem juros",
        "tituloDetalhe": "Motorola Moto Maxx 2 64gb",
        "marca": "Motorola",
        "modelo": "Moto Maxx",
        "cor": "Preto",
        "chip": "Nano Chip",
        "qtd_chip": "Single Chip",
        "memoria_interna": "64GB",
        "memoria_ram": "3GB",
        "processador": "Snapdragon 805 Qualcomm APQ8084",
        "sistema": "Android",
        "versao": "4.4.4 KitKat",
        "tipo_tela": "AMOLED",
        "tamanho_display": "5.2'",
        "resolucao": "1440 x 2560 pixel",
        "camera_traseira": "21MP",
        "camera_frontal": "2MP",
        "lado": "https://imagens.trocafone.com/images/phones/dt-moto-maxx-2a-g-2.png",
        "traseira":  "https://imagens.trocafone.com/images/phones/dt-moto-maxx-2a-g-3.png"
    },

    {
        "id": "3",
        "imagem": "https://imagens.trocafone.com/images/phones/dt-s8-preto-1.jpg",
        "titulo": "Samsung Galaxy S8 Plus",
        "preco": "1970,90",
        "parcela": "ou 12x R$ 50,90 sem juros",
        "tituloDetalhe": "Samsung Galaxy S8 Plus 64GB",
        "marca": "Samsung",
        "modelo": "Galaxy S8 Plus",
        "cor": "Preto",
        "chip": "Dois chips",
        "memoria_interna": "64GB",
        "memoria_ram": "4 GB / 6 GB",
        "processador": "Octa-core 2.3 GHz + 1.7 GHz",
        "sistema": "Android",
        "versao": "4.4.4 KitKat",
        "tipo_tela": "AMOLED",
        "tamanho_display": "6.2'",
        "resolucao": "2960 x 1440 pixels",
        "camera_traseira": "12 MP",
        "camera_frontal": "8 MP",
        "lado": "https://imagens.trocafone.com/images/phones/dt-s8-preto-2.jpg",
        "traseira": "https://imagens.trocafone.com/images/phones/dt-s8-preto-3.jpg"
    },

    {
        "id": "4",
        "imagem": "https://imagens.trocafone.com/images/phones/dt-5979f872-moto-g5-plus-platinum-1.jpg",
        "titulo": "Motorola Moto G5 Plus",
        "preco": "859,90",
        "parcela": "ou 12x R$ 39,90 sem juros",
        "tituloDetalhe": "Motorola Moto G 5S Dual Chip Android 7.1.1 Nougat",
        "marca": "Motorola",
        "modelo": "Moto G 5S",
        "cor": "Platinum",
        "chip": "Nano Chip",
        "qtd_chip": "Dual Chip",
        "memoria_interna": "32GB",
        "memoria_ram": "2GB",
        "processador": "Snapdradon 430",
        "sistema": "Android",
        "versao": "7.1.1 Nougat",
        "tipo_tela": "LCD IPS",
        "tamanho_display": "5.2'",
        "resolucao": "Full HD - 1920x1080",
        "camera_traseira": "16MP",
        "camera_frontal": "5MP",
        "lado": "https://imagens.trocafone.com/images/phones/dt-moto-g5-plus-platinum-2.jpg",
        "traseira": "https://imagens.trocafone.com/images/phones/dt-moto-g5-plus-platinum-3.jpg"
    },

    {
        "id": "5",
        "imagem": "https://imagens.trocafone.com/images/phones/dt-s7-edge-dourado-1.png",
        "titulo": "Samsung Galaxy S7 Edge",
        "preco": "1689,99",
        "parcela": "ou R$ 65,60 sem juros",
        "tituloDetalhe": "Smartphone Samsung Galaxy S7 Edge Android 6.0",
        "marca": "Samsung",
        "modelo": "Galaxy S7 Edge",
        "cor": "Dourado",
        "chip": "Nano Chip",
        "qtd_chip": "Single Chip",
        "memoria_interna": "32GB",
        "memoria_ram": "4GB",
        "processador": "Octa-Core 2.3GHz + 1.6GHz",
        "sistema": "Android",
        "versao": "Android 6.0",
        "tipo_tela": "Super AMOLED",
        "tamanho_display": "5.5'",
        "resolucao": "2560x1440 (Quad HD)",
        "camera_traseira": "12MP",
        "camera_frontal": "5MP",
        "lado": "https://imagens.trocafone.com/images/phones/dt-s7-edge-dourado-3.png",
        "traseira": "https://imagens.trocafone.com/images/phones/dt-s7-edge-dourado-4.png"
    },

    {
        "id": "6",
        "imagem": "https://imagens.trocafone.com/images/phones/dt-prata-frente.jpg",
        "titulo": "Iphone SE Prata",
        "preco": "1259,99",
        "parcela": "ou 12x de R$ 39,90 sem juros",
        "tituloDetalhe": "iPhone SE 32GB Prata IOS 4G Câmera 12MP - Apple",
        "marca": "Apple",
        "modelo": "iPhone SE",
        "cor": "Prata",
        "chip": "Nano Chip",
        "qtd_chip": "Single Chip",
        "memoria_interna": "32GB",
        "memoria_ram": "2GB",
        "processador": "A9",
        "sistema": "Iphone IOS",
        "versao": "iOS 10",
        "tipo_tela": "Retina Display",
        "tamanho_display": "4'",
        "resolucao": "1136 x 640 pixel",
        "camera_traseira": "12MP",
        "camera_frontal": "1.2MP",
        "lado": "https://imagens.trocafone.com/images/phones/dt-prata-lado.jpg",
        "traseira": "https://imagens.trocafone.com/images/phones/dt-prata-tras.jpg"
    },

    {
        "id": "7",
        "imagem": "https://imagens.trocafone.com/images/phones/dt-motorola-moto-x-style-32gb-preto.png",
        "titulo": "Motorola Moto X Style",
        "preco": "2000,00",
        "parcela": "ou 12x R$ 49,90 sem juros",
        "tituloDetalhe": "Moto X Style Xt1572 32gb Preto",
        "marca": "Motorola",
        "modelo": "Moto X",
        "cor": "Preto",
        "chip": "Nano Chip",
        "qtd_chip": "Single Chip",
        "memoria_interna": "32GB",
        "memoria_ram": "3GB",
        "processador": "Dual-core 1.8 GHz Cortex-A57",
        "sistema": "Android",
        "versao": "5.1.1 Lollipop",
        "tipo_tela": "TFT LCD",
        "tamanho_display": "5.7'",
        "resolucao": "1440 x 2560 pixel",
        "camera_traseira": "12MP",
        "camera_frontal": "2MP",
        "lado": "https://imagens.trocafone.com/images/phones/dt-x-style-pret-2.png",
        "traseira": "https://imagens.trocafone.com/images/phones/dt-x-style-pret-3.png"
    },

    {
        "id": "8",
        "imagem": "https://imagens.trocafone.com/images/phones/dt-galaxy-s6-flat-bran-1.png",
        "titulo": "Samsung Galaxy S6 Flat",
        "preco": "659,00",
        "parcela": "ou 12x R$ 25,90 sem juros",
        "tituloDetalhe": "Samsung Galaxy S6 Flat Branco",
        "marca": "Samsung",
        "modelo": "Galaxy S6 Flat",
        "cor": "Branco",
        "chip": "Nano Chip",
        "qtd_chip": "Single Chip",
        "memoria_interna": "32GB",
        "memoria_ram": "3GB",
        "processador": "Octa-Core 1.5 GHz + 2.1 GHz",
        "sistema": "Android",
        "versao": "5.1.1 Lollipop",
        "tipo_tela": "TFT LCD",
        "tamanho_display": "5.1'",
        "resolucao": "1440 x 2560 pixels",
        "camera_traseira": "12MP",
        "camera_frontal": "2MP",
        "lado": "https://imagens.trocafone.com/images/phones/dt-galaxy-s6-flat-bran-2.png",
        "traseira": "https://imagens.trocafone.com/images/phones/dt-galaxy-s6-flat-bran-3.png"
    },

    {
        "id": "9",
        "imagem": "https://imagens.trocafone.com/images/phones/dt-5b3134b3-zenfone-4-verde-frente.png",
        "titulo": "Zenfone 4 Verde",
        "preco": "1659,55",
        "parcela": "ou 12x R$ 49,90 sem juros",
        "tituloDetalhe": "Zenfone 4 4GB Ram Verde",
        "marca": "Asus",
        "modelo": "Zenfone 4",
        "cor": "Verde",
        "chip": "Nano Chip",
        "qtd_chip": "Single Chip",
        "memoria_interna": "8GB",
        "memoria_ram": "4GB",
        "processador": "QUALCOMM SNAPDRAGON SDN630 2,2 GHz, 2 MB Cache",
        "sistema": "Android",
        "versao": "7",
        "tipo_tela": "AMOLED",
        "tamanho_display": "5.5'",
        "resolucao": "1440 x 2560 pixel",
        "camera_traseira": "12 + 8MP (Dual Traseira)",
        "camera_frontal": "8MP",
        "lado": "https://imagens.trocafone.com/images/phones/dt-5b3134b4-zenfone-4-verde-perfil.png",
        "traseira": "https://imagens.trocafone.com/images/phones/dt-5b3134b5-zenfone-4-verde-traseira.png"
    },

    {
        "id": "10",
        "imagem": "https://imagens.trocafone.com/images/phones/dt-zenfone-4-selfie-pro-vermelho-frente.png",
        "titulo": "Zenfone 4 Selfie Pro",
        "preco": "1789,00",
        "parcela": "ou 12x R$ 69,99 sem juros",
        "tituloDetalhe": "Zenfone 4 Selfie Pro 4GB Ram Vermelho",
        "marca": "Asus",
        "modelo": "Zenfone 4",
        "cor": "Vermelho",
        "chip": "Nano Chip",
        "qtd_chip": "Single Chip",
        "memoria_interna": "16GB",
        "memoria_ram": "4GB",
        "processador": "QUALCOMM SNAPDRAGON SDN630 2,2 GHz, 2 MB Cache",
        "sistema": "Android",
        "versao": "7",
        "tipo_tela": "AMOLED",
        "tamanho_display": "5.5'",
        "resolucao": "1440 x 2560 pixel",
        "camera_traseira": "18 + 8MP (Dual Traseira)",
        "camera_frontal": "8MP",
        "lado": "https://imagens.trocafone.com/images/phones/dt-zenfone-4-selfie-pro-vermelho-perfil.png",
        "traseira": "https://imagens.trocafone.com/images/phones/dt-zenfone-4-selfie-pro-vermelho-traseira.png"
    },

    {
        "id": "11",
        "imagem": "https://imagens.trocafone.com/images/phones/dt-5a5f3e54-zenfone-3-preto-1.jpg",
        "titulo": "Zenfone 3 Preto",
        "preco": "1289,66",
        "parcela": "ou 12x R$ 45,60 sem juros",
        "tituloDetalhe": "Smartphone Asus Zenfone 3 Dual Chip ",
        "marca": "Asus",
        "modelo": "ZE520KL-1A090BR",
        "cor": "Preto",
        "chip": "Micro Chip",
        "qtd_chip": "Dual Chip",
        "memoria_interna": "16GB",
        "memoria_ram": "2GB",
        "processador": "Qualcomm Snapdragon 625 Octa-core 2.0 GHz",
        "sistema": "Android",
        "versao": "6",
        "tipo_tela": "LCD IPS",
        "tamanho_display": "5.2'",
        "resolucao": "1920x1080",
        "camera_traseira": "16MP",
        "camera_frontal": "8MP",
        "lado": "https://imagens.trocafone.com/images/phones/dt-5aa96fd9-zenfone-3-preto-2.jpg",
        "traseira": "https://imagens.trocafone.com/images/phones/dt-5aa96fd9-zenfone-3-preto-3.jpg"
    }
]